[{"gap_size":2,"success_rate":0.10716728193789118,"theoretical_boost":1.0,"shield_score":0,"shield_primes":""},{"gap_size":4,"success_rate":0.16055811362174383,"theoretical_boost":1.5,"shield_score":1,"shield_primes":"3"},{"gap_size":6,"success_rate":0.1008067436140255,"theoretical_boost":1.25,"shield_score":1,"shield_primes":"5"},{"gap_size":8,"success_rate":0.13134756330820016,"theoretical_boost":1.1666666666666667,"shield_score":1,"shield_primes":"7"},{"gap_size":10,"success_rate":0.14293581177737277,"theoretical_boost":1.5,"shield_score":1,"shield_primes":"3"},{"gap_size":12,"success_rate":0.07215195849948881,"theoretical_boost":1.1,"shield_score":1,"shield_primes":"11"},{"gap_size":14,"success_rate":0.18799220146354428,"theoretical_boost":1.0833333333333333,"shield_score":1,"shield_primes":"13"},{"gap_size":16,"success_rate":0.176140256985413,"theoretical_boost":1.875,"shield_score":2,"shield_primes":"3,5"},{"gap_size":18,"success_rate":0.059633271183325016,"theoretical_boost":1.0625,"shield_score":1,"shield_primes":"17"},{"gap_size":20,"success_rate":0.16071167181914023,"theoretical_boost":1.0555555555555556,"shield_score":1,"shield_primes":"19"},{"gap_size":22,"success_rate":0.148806857962679,"theoretical_boost":1.75,"shield_score":2,"shield_primes":"3,7"},{"gap_size":24,"success_rate":0.08628563608301507,"theoretical_boost":1.0454545454545454,"shield_score":1,"shield_primes":"23"},{"gap_size":26,"success_rate":0.1662767900606028,"theoretical_boost":1.25,"shield_score":1,"shield_primes":"5"},{"gap_size":28,"success_rate":0.11615486002380165,"theoretical_boost":1.5,"shield_score":1,"shield_primes":"3"},{"gap_size":30,"success_rate":0.06605996076200499,"theoretical_boost":1.0357142857142858,"shield_score":1,"shield_primes":"29"},{"gap_size":32,"success_rate":0.12471779334869629,"theoretical_boost":1.0333333333333334,"shield_score":1,"shield_primes":"31"},{"gap_size":34,"success_rate":0.23032364137194922,"theoretical_boost":1.6500000000000001,"shield_score":2,"shield_primes":"3,11"},{"gap_size":36,"success_rate":0.10344303659165327,"theoretical_boost":1.4583333333333335,"shield_score":2,"shield_primes":"5,7"},{"gap_size":38,"success_rate":0.12020133176369395,"theoretical_boost":1.0277777777777777,"shield_score":1,"shield_primes":"37"},{"gap_size":40,"success_rate":0.13985942846573568,"theoretical_boost":1.625,"shield_score":2,"shield_primes":"3,13"},{"gap_size":42,"success_rate":0.06353252533380271,"theoretical_boost":1.025,"shield_score":1,"shield_primes":"41"},{"gap_size":44,"success_rate":0.17063192637192853,"theoretical_boost":1.0238095238095237,"shield_score":1,"shield_primes":"43"},{"gap_size":46,"success_rate":0.1647914674952199,"theoretical_boost":1.875,"shield_score":2,"shield_primes":"3,5"},{"gap_size":48,"success_rate":0.06503628429424492,"theoretical_boost":1.0217391304347827,"shield_score":1,"shield_primes":"47"},{"gap_size":50,"success_rate":0.1572031237616821,"theoretical_boost":1.1666666666666667,"shield_score":1,"shield_primes":"7"},{"gap_size":52,"success_rate":0.1268408976257506,"theoretical_boost":1.59375,"shield_score":2,"shield_primes":"3,17"},{"gap_size":54,"success_rate":0.09586759958515316,"theoretical_boost":1.0192307692307692,"shield_score":1,"shield_primes":"53"},{"gap_size":56,"success_rate":0.20679365559769605,"theoretical_boost":1.375,"shield_score":2,"shield_primes":"5,11"},{"gap_size":58,"success_rate":0.11475256666739948,"theoretical_boost":1.5833333333333335,"shield_score":2,"shield_primes":"3,19"},{"gap_size":60,"success_rate":0.06193540752852713,"theoretical_boost":1.0172413793103448,"shield_score":1,"shield_primes":"59"},{"gap_size":62,"success_rate":0.14125374270928884,"theoretical_boost":1.0166666666666666,"shield_score":1,"shield_primes":"61"},{"gap_size":64,"success_rate":0.2179300720464729,"theoretical_boost":1.75,"shield_score":2,"shield_primes":"3,7"},{"gap_size":66,"success_rate":0.09161527213347664,"theoretical_boost":1.3541666666666665,"shield_score":2,"shield_primes":"5,13"},{"gap_size":68,"success_rate":0.11431512738132947,"theoretical_boost":1.0151515151515151,"shield_score":1,"shield_primes":"67"},{"gap_size":70,"success_rate":0.13307954509254244,"theoretical_boost":1.5681818181818181,"shield_score":2,"shield_primes":"3,23"},{"gap_size":72,"success_rate":0.056204258544326285,"theoretical_boost":1.0142857142857142,"shield_score":1,"shield_primes":"71"},{"gap_size":74,"success_rate":0.16487541182867926,"theoretical_boost":1.0138888888888888,"shield_score":1,"shield_primes":"73"},{"gap_size":76,"success_rate":0.22577250376499192,"theoretical_boost":1.875,"shield_score":2,"shield_primes":"3,5"},{"gap_size":78,"success_rate":0.07038067475050563,"theoretical_boost":1.2833333333333334,"shield_score":2,"shield_primes":"7,11"},{"gap_size":80,"success_rate":0.1221180075482979,"theoretical_boost":1.0128205128205128,"shield_score":1,"shield_primes":"79"},{"gap_size":82,"success_rate":0.11523879732504871,"theoretical_boost":1.5,"shield_score":1,"shield_primes":"3"},{"gap_size":84,"success_rate":0.09269054907335067,"theoretical_boost":1.0121951219512195,"shield_score":1,"shield_primes":"83"},{"gap_size":86,"success_rate":0.18159248731695032,"theoretical_boost":1.328125,"shield_score":2,"shield_primes":"5,17"},{"gap_size":88,"success_rate":0.12099175843202438,"theoretical_boost":1.5535714285714288,"shield_score":2,"shield_primes":"3,29"},{"gap_size":90,"success_rate":0.08252234872625179,"theoretical_boost":1.0113636363636365,"shield_score":1,"shield_primes":"89"},{"gap_size":92,"success_rate":0.1537703557722228,"theoretical_boost":1.2638888888888888,"shield_score":2,"shield_primes":"7,13"},{"gap_size":94,"success_rate":0.18490010753296734,"theoretical_boost":1.5500000000000003,"shield_score":2,"shield_primes":"3,31"},{"gap_size":96,"success_rate":0.09032112748568119,"theoretical_boost":1.3194444444444444,"shield_score":2,"shield_primes":"5,19"},{"gap_size":98,"success_rate":0.126306027820711,"theoretical_boost":1.0104166666666667,"shield_score":1,"shield_primes":"97"},{"gap_size":100,"success_rate":0.13372781065088757,"theoretical_boost":1.6500000000000001,"shield_score":2,"shield_primes":"3,11"},{"gap_size":102,"success_rate":0.053186263564506765,"theoretical_boost":1.0,"shield_score":0,"shield_primes":""},{"gap_size":104,"success_rate":0.1962172647914646,"theoretical_boost":1.0,"shield_score":0,"shield_primes":""},{"gap_size":106,"success_rate":0.2005963986695722,"theoretical_boost":2.1875,"shield_score":3,"shield_primes":"3,5,7"},{"gap_size":108,"success_rate":0.055760398473381205,"theoretical_boost":1.0,"shield_score":0,"shield_primes":""},{"gap_size":110,"success_rate":0.12664092664092663,"theoretical_boost":1.0,"shield_score":0,"shield_primes":""},{"gap_size":112,"success_rate":0.11262081524022972,"theoretical_boost":1.5416666666666665,"shield_score":2,"shield_primes":"3,37"},{"gap_size":114,"success_rate":0.07739625413147264,"theoretical_boost":1.0,"shield_score":0,"shield_primes":""},{"gap_size":116,"success_rate":0.18089171974522292,"theoretical_boost":1.3068181818181817,"shield_score":2,"shield_primes":"5,23"},{"gap_size":118,"success_rate":0.15970679697912038,"theoretical_boost":1.625,"shield_score":2,"shield_primes":"3,13"},{"gap_size":120,"success_rate":0.08990749402349028,"theoretical_boost":1.2395833333333335,"shield_score":2,"shield_primes":"7,17"},{"gap_size":122,"success_rate":0.11663865546218487,"theoretical_boost":1.1,"shield_score":1,"shield_primes":"11"},{"gap_size":124,"success_rate":0.15625,"theoretical_boost":1.5374999999999999,"shield_score":2,"shield_primes":"3,41"},{"gap_size":126,"success_rate":0.08579225652396384,"theoretical_boost":1.25,"shield_score":1,"shield_primes":"5"},{"gap_size":128,"success_rate":0.11062163485070974,"theoretical_boost":1.0,"shield_score":0,"shield_primes":""},{"gap_size":130,"success_rate":0.12726626377532882,"theoretical_boost":1.5357142857142856,"shield_score":2,"shield_primes":"3,43"},{"gap_size":132,"success_rate":0.07179487179487179,"theoretical_boost":1.0,"shield_score":0,"shield_primes":""},{"gap_size":134,"success_rate":0.21654337592468056,"theoretical_boost":1.2314814814814816,"shield_score":2,"shield_primes":"7,19"},{"gap_size":136,"success_rate":0.16037008481110254,"theoretical_boost":1.875,"shield_score":2,"shield_primes":"3,5"},{"gap_size":138,"success_rate":0.05639242950946311,"theoretical_boost":1.0,"shield_score":0,"shield_primes":""},{"gap_size":140,"success_rate":0.1424802110817942,"theoretical_boost":1.0,"shield_score":0,"shield_primes":""},{"gap_size":142,"success_rate":0.1311647429171039,"theoretical_boost":1.532608695652174,"shield_score":2,"shield_primes":"3,47"},{"gap_size":144,"success_rate":0.09710610932475884,"theoretical_boost":1.1916666666666667,"shield_score":2,"shield_primes":"11,13"},{"gap_size":146,"success_rate":0.18862275449101795,"theoretical_boost":1.2946428571428572,"shield_score":2,"shield_primes":"5,29"},{"gap_size":148,"success_rate":0.1298342541436464,"theoretical_boost":1.75,"shield_score":2,"shield_primes":"3,7"},{"gap_size":150,"success_rate":0.07738896366083446,"theoretical_boost":1.0,"shield_score":0,"shield_primes":""},{"gap_size":152,"success_rate":0.13043478260869565,"theoretical_boost":1.0,"shield_score":0,"shield_primes":""},{"gap_size":154,"success_rate":0.15265866209262435,"theoretical_boost":1.59375,"shield_score":2,"shield_primes":"3,17"},{"gap_size":156,"success_rate":0.07894736842105263,"theoretical_boost":1.2916666666666667,"shield_score":2,"shield_primes":"5,31"},{"gap_size":158,"success_rate":0.11437908496732026,"theoretical_boost":1.0,"shield_score":0,"shield_primes":""},{"gap_size":160,"success_rate":0.16666666666666666,"theoretical_boost":1.5288461538461537,"shield_score":2,"shield_primes":"3,53"},{"gap_size":162,"success_rate":0.07677902621722846,"theoretical_boost":1.2196969696969697,"shield_score":2,"shield_primes":"7,23"},{"gap_size":164,"success_rate":0.1862348178137652,"theoretical_boost":1.0,"shield_score":0,"shield_primes":""},{"gap_size":166,"success_rate":0.16483516483516483,"theoretical_boost":2.0625,"shield_score":3,"shield_primes":"3,5,11"},{"gap_size":168,"success_rate":0.06772009029345373,"theoretical_boost":1.0,"shield_score":0,"shield_primes":""},{"gap_size":170,"success_rate":0.11616161616161616,"theoretical_boost":1.0833333333333333,"shield_score":1,"shield_primes":"13"},{"gap_size":172,"success_rate":0.12025316455696203,"theoretical_boost":1.5833333333333335,"shield_score":2,"shield_primes":"3,19"},{"gap_size":174,"success_rate":0.11372549019607843,"theoretical_boost":1.0,"shield_score":0,"shield_primes":""},{"gap_size":176,"success_rate":0.234375,"theoretical_boost":1.4583333333333335,"shield_score":2,"shield_primes":"5,7"},{"gap_size":178,"success_rate":0.11320754716981132,"theoretical_boost":1.5258620689655171,"shield_score":2,"shield_primes":"3,59"},{"gap_size":180,"success_rate":0.06,"theoretical_boost":1.0,"shield_score":0,"shield_primes":""},{"gap_size":182,"success_rate":0.15,"theoretical_boost":1.0,"shield_score":0,"shield_primes":""},{"gap_size":184,"success_rate":0.16853932584269662,"theoretical_boost":1.525,"shield_score":2,"shield_primes":"3,61"},{"gap_size":186,"success_rate":0.1782178217821782,"theoretical_boost":1.284722222222222,"shield_score":2,"shield_primes":"5,37"},{"gap_size":188,"success_rate":0.030303030303030304,"theoretical_boost":1.1687500000000002,"shield_score":2,"shield_primes":"11,17"},{"gap_size":190,"success_rate":0.1111111111111111,"theoretical_boost":1.75,"shield_score":2,"shield_primes":"3,7"},{"gap_size":192,"success_rate":0.06756756756756757,"theoretical_boost":1.0,"shield_score":0,"shield_primes":""},{"gap_size":194,"success_rate":0.28125,"theoretical_boost":1.0,"shield_score":0,"shield_primes":""},{"gap_size":196,"success_rate":0.14634146341463414,"theoretical_boost":2.03125,"shield_score":3,"shield_primes":"3,5,13"},{"gap_size":198,"success_rate":0.0410958904109589,"theoretical_boost":1.0,"shield_score":0,"shield_primes":""},{"gap_size":200,"success_rate":0.17857142857142858,"theoretical_boost":1.0,"shield_score":0,"shield_primes":""},{"gap_size":202,"success_rate":0.21739130434782608,"theoretical_boost":1.5227272727272727,"shield_score":2,"shield_primes":"3,67"},{"gap_size":204,"success_rate":0.15217391304347827,"theoretical_boost":1.2083333333333335,"shield_score":2,"shield_primes":"7,29"},{"gap_size":206,"success_rate":0.15384615384615385,"theoretical_boost":1.28125,"shield_score":2,"shield_primes":"5,41"},{"gap_size":208,"success_rate":0.1111111111111111,"theoretical_boost":1.5681818181818181,"shield_score":2,"shield_primes":"3,23"},{"gap_size":210,"success_rate":0.125,"theoretical_boost":1.1611111111111112,"shield_score":2,"shield_primes":"11,19"},{"gap_size":216,"success_rate":0.13333333333333333,"theoretical_boost":1.2797619047619047,"shield_score":2,"shield_primes":"5,43"},{"gap_size":220,"success_rate":0.3333333333333333,"theoretical_boost":1.5208333333333333,"shield_score":2,"shield_primes":"3,73"},{"gap_size":224,"success_rate":0.5,"theoretical_boost":1.0,"shield_score":0,"shield_primes":""},{"gap_size":242,"success_rate":0.25,"theoretical_boost":1.0,"shield_score":0,"shield_primes":""},{"gap_size":246,"success_rate":0.25,"theoretical_boost":1.4583333333333335,"shield_score":2,"shield_primes":"5,7"},{"gap_size":248,"success_rate":0.25,"theoretical_boost":1.1435185185185184,"shield_score":2,"shield_primes":"13,19"},{"gap_size":250,"success_rate":0.25,"theoretical_boost":1.5182926829268293,"shield_score":2,"shield_primes":"3,83"}]
