[{"gap_size":2,"success_rate":0.09593214147365896,"theoretical_boost":1.5,"shield_score":1,"shield_primes":"3"},{"gap_size":4,"success_rate":0.1439254391773396,"theoretical_boost":1.875,"shield_score":2,"shield_primes":"3,5"},{"gap_size":6,"success_rate":0.09043455652364013,"theoretical_boost":1.4583333333333335,"shield_score":2,"shield_primes":"5,7"},{"gap_size":8,"success_rate":0.1180452492755126,"theoretical_boost":1.75,"shield_score":2,"shield_primes":"3,7"},{"gap_size":10,"success_rate":0.12735015858960846,"theoretical_boost":1.6500000000000001,"shield_score":2,"shield_primes":"3,11"},{"gap_size":12,"success_rate":0.06431756641118849,"theoretical_boost":1.1916666666666667,"shield_score":2,"shield_primes":"11,13"},{"gap_size":14,"success_rate":0.16809520151234106,"theoretical_boost":2.03125,"shield_score":3,"shield_primes":"3,5,13"},{"gap_size":16,"success_rate":0.1576188271813765,"theoretical_boost":1.9921875,"shield_score":3,"shield_primes":"3,5,17"},{"gap_size":18,"success_rate":0.05371975331975936,"theoretical_boost":1.121527777777778,"shield_score":2,"shield_primes":"17,19"},{"gap_size":20,"success_rate":0.14408864909286115,"theoretical_boost":1.8472222222222223,"shield_score":3,"shield_primes":"3,7,19"},{"gap_size":22,"success_rate":0.13299072879498414,"theoretical_boost":1.8295454545454546,"shield_score":3,"shield_primes":"3,7,23"},{"gap_size":24,"success_rate":0.07713206964816542,"theoretical_boost":1.3068181818181817,"shield_score":2,"shield_primes":"5,23"},{"gap_size":26,"success_rate":0.1487610741422728,"theoretical_boost":1.875,"shield_score":2,"shield_primes":"3,5"},{"gap_size":28,"success_rate":0.10407110581933944,"theoretical_boost":1.5535714285714288,"shield_score":2,"shield_primes":"3,29"},{"gap_size":30,"success_rate":0.059242225724086675,"theoretical_boost":1.0702380952380954,"shield_score":2,"shield_primes":"29,31"},{"gap_size":32,"success_rate":0.11211101288765078,"theoretical_boost":1.7050000000000003,"shield_score":3,"shield_primes":"3,11,31"},{"gap_size":34,"success_rate":0.20616840147062437,"theoretical_boost":2.40625,"shield_score":4,"shield_primes":"3,5,7,11"},{"gap_size":36,"success_rate":0.09340746781882192,"theoretical_boost":1.4988425925925926,"shield_score":3,"shield_primes":"5,7,37"},{"gap_size":38,"success_rate":0.10819792040833562,"theoretical_boost":1.6701388888888888,"shield_score":3,"shield_primes":"3,13,37"},{"gap_size":40,"success_rate":0.12495240580302511,"theoretical_boost":1.665625,"shield_score":3,"shield_primes":"3,13,41"},{"gap_size":42,"success_rate":0.0564362042151439,"theoretical_boost":1.0494047619047617,"shield_score":2,"shield_primes":"41,43"},{"gap_size":44,"success_rate":0.15253609170169047,"theoretical_boost":1.919642857142857,"shield_score":3,"shield_primes":"3,5,43"},{"gap_size":46,"success_rate":0.14796189856880806,"theoretical_boost":1.9157608695652175,"shield_score":3,"shield_primes":"3,5,47"},{"gap_size":48,"success_rate":0.058825317419624226,"theoretical_boost":1.1920289855072466,"shield_score":2,"shield_primes":"7,47"},{"gap_size":50,"success_rate":0.1410771256323193,"theoretical_boost":1.859375,"shield_score":3,"shield_primes":"3,7,17"},{"gap_size":52,"success_rate":0.11220132132797764,"theoretical_boost":1.6243990384615383,"shield_score":3,"shield_primes":"3,17,53"},{"gap_size":54,"success_rate":0.08568529542387185,"theoretical_boost":1.4014423076923075,"shield_score":3,"shield_primes":"5,11,53"},{"gap_size":56,"success_rate":0.18641469271397298,"theoretical_boost":2.1770833333333335,"shield_score":4,"shield_primes":"3,5,11,19"},{"gap_size":58,"success_rate":0.10276780343200184,"theoretical_boost":1.610632183908046,"shield_score":3,"shield_primes":"3,19,59"},{"gap_size":60,"success_rate":0.055714041180634416,"theoretical_boost":1.0341954022988504,"shield_score":2,"shield_primes":"59,61"},{"gap_size":62,"success_rate":0.12619770344554107,"theoretical_boost":1.7791666666666666,"shield_score":3,"shield_primes":"3,7,61"},{"gap_size":64,"success_rate":0.19585534618807393,"theoretical_boost":2.3697916666666665,"shield_score":4,"shield_primes":"3,5,7,13"},{"gap_size":66,"success_rate":0.08268164383888625,"theoretical_boost":1.3746843434343432,"shield_score":3,"shield_primes":"5,13,67"},{"gap_size":68,"success_rate":0.10239665491220042,"theoretical_boost":1.5919421487603305,"shield_score":3,"shield_primes":"3,23,67"},{"gap_size":70,"success_rate":0.12099439835531506,"theoretical_boost":1.5905844155844155,"shield_score":3,"shield_primes":"3,23,71"},{"gap_size":72,"success_rate":0.05063791324186567,"theoretical_boost":1.0283730158730158,"shield_score":2,"shield_primes":"71,73"},{"gap_size":74,"success_rate":0.14814954659780882,"theoretical_boost":1.9010416666666665,"shield_score":3,"shield_primes":"3,5,73"},{"gap_size":76,"success_rate":0.20109939645213185,"theoretical_boost":2.40625,"shield_score":4,"shield_primes":"3,5,7,11"},{"gap_size":78,"success_rate":0.06511440202133632,"theoretical_boost":1.2997863247863248,"shield_score":3,"shield_primes":"7,11,79"},{"gap_size":80,"success_rate":0.10808468073518666,"theoretical_boost":1.5192307692307692,"shield_score":2,"shield_primes":"3,79"},{"gap_size":82,"success_rate":0.1027068292774877,"theoretical_boost":1.5182926829268293,"shield_score":2,"shield_primes":"3,83"},{"gap_size":84,"success_rate":0.08361173904314861,"theoretical_boost":1.3443216463414633,"shield_score":3,"shield_primes":"5,17,83"},{"gap_size":86,"success_rate":0.16707021791767554,"theoretical_boost":2.063337053571429,"shield_score":4,"shield_primes":"3,5,17,29"},{"gap_size":88,"success_rate":0.10665870493982499,"theoretical_boost":1.5712256493506498,"shield_score":3,"shield_primes":"3,29,89"},{"gap_size":90,"success_rate":0.07449692817618261,"theoretical_boost":1.2782512626262628,"shield_score":3,"shield_primes":"7,13,89"},{"gap_size":92,"success_rate":0.1392164552511292,"theoretical_boost":1.9590277777777778,"shield_score":4,"shield_primes":"3,7,13,31"},{"gap_size":94,"success_rate":0.1659513327315932,"theoretical_boost":2.0451388888888893,"shield_score":4,"shield_primes":"3,5,19,31"},{"gap_size":96,"success_rate":0.0816757842197468,"theoretical_boost":1.3331886574074074,"shield_score":3,"shield_primes":"5,19,97"},{"gap_size":98,"success_rate":0.11259037413135543,"theoretical_boost":1.6671875000000003,"shield_score":3,"shield_primes":"3,11,97"},{"gap_size":100,"success_rate":0.12322400002974719,"theoretical_boost":1.6500000000000001,"shield_score":2,"shield_primes":"3,11"},{"gap_size":102,"success_rate":0.04858131106425786,"theoretical_boost":1.0,"shield_score":0,"shield_primes":""},{"gap_size":104,"success_rate":0.1807691850159999,"theoretical_boost":2.1875,"shield_score":3,"shield_primes":"3,5,7"},{"gap_size":106,"success_rate":0.18288379639018454,"theoretical_boost":2.1875,"shield_score":3,"shield_primes":"3,5,7"},{"gap_size":108,"success_rate":0.049836387937258995,"theoretical_boost":1.0,"shield_score":0,"shield_primes":""},{"gap_size":110,"success_rate":0.11478131225177594,"theoretical_boost":1.5416666666666665,"shield_score":2,"shield_primes":"3,37"},{"gap_size":112,"success_rate":0.10277373886650935,"theoretical_boost":1.5416666666666665,"shield_score":2,"shield_primes":"3,37"},{"gap_size":114,"success_rate":0.07322707560936621,"theoretical_boost":1.3068181818181817,"shield_score":2,"shield_primes":"5,23"},{"gap_size":116,"success_rate":0.16109306779923147,"theoretical_boost":2.1235795454545454,"shield_score":4,"shield_primes":"3,5,13,23"},{"gap_size":118,"success_rate":0.14342161081146598,"theoretical_boost":2.0143229166666665,"shield_score":4,"shield_primes":"3,7,13,17"},{"gap_size":120,"success_rate":0.08088462815124868,"theoretical_boost":1.3635416666666669,"shield_score":3,"shield_primes":"7,11,17"},{"gap_size":122,"success_rate":0.10784880158271618,"theoretical_boost":1.69125,"shield_score":3,"shield_primes":"3,11,41"},{"gap_size":124,"success_rate":0.1440654935797269,"theoretical_boost":1.9218749999999998,"shield_score":3,"shield_primes":"3,5,41"},{"gap_size":126,"success_rate":0.07646554543124552,"theoretical_boost":1.25,"shield_score":1,"shield_primes":"5"},{"gap_size":128,"success_rate":0.10074663046640163,"theoretical_boost":1.5357142857142856,"shield_score":2,"shield_primes":"3,43"},{"gap_size":130,"success_rate":0.1130944994947973,"theoretical_boost":1.5357142857142856,"shield_score":2,"shield_primes":"3,43"},{"gap_size":132,"success_rate":0.06965933627649186,"theoretical_boost":1.2314814814814816,"shield_score":2,"shield_primes":"7,19"},{"gap_size":134,"success_rate":0.1947902700632063,"theoretical_boost":2.3090277777777777,"shield_score":4,"shield_primes":"3,5,7,19"},{"gap_size":136,"success_rate":0.14459180459810336,"theoretical_boost":1.875,"shield_score":2,"shield_primes":"3,5"},{"gap_size":138,"success_rate":0.04958508540170431,"theoretical_boost":1.0,"shield_score":0,"shield_primes":""},{"gap_size":140,"success_rate":0.11996363849627588,"theoretical_boost":1.532608695652174,"shield_score":2,"shield_primes":"3,47"},{"gap_size":142,"success_rate":0.11612298277648916,"theoretical_boost":1.8263586956521742,"shield_score":4,"shield_primes":"3,11,13,47"},{"gap_size":144,"success_rate":0.08961561173129376,"theoretical_boost":1.5427827380952381,"shield_score":4,"shield_primes":"5,11,13,29"},{"gap_size":146,"success_rate":0.18124141539669042,"theoretical_boost":2.265625,"shield_score":4,"shield_primes":"3,5,7,29"},{"gap_size":148,"success_rate":0.11977949547606208,"theoretical_boost":1.75,"shield_score":2,"shield_primes":"3,7"},{"gap_size":150,"success_rate":0.057602698607815674,"theoretical_boost":1.0,"shield_score":0,"shield_primes":""},{"gap_size":152,"success_rate":0.11276200583709206,"theoretical_boost":1.59375,"shield_score":2,"shield_primes":"3,17"},{"gap_size":154,"success_rate":0.1585822212808021,"theoretical_boost":2.05859375,"shield_score":4,"shield_primes":"3,5,17,31"},{"gap_size":156,"success_rate":0.07129981974764671,"theoretical_boost":1.2916666666666667,"shield_score":2,"shield_primes":"5,31"},{"gap_size":158,"success_rate":0.09558117195004803,"theoretical_boost":1.5288461538461537,"shield_score":2,"shield_primes":"3,53"},{"gap_size":160,"success_rate":0.15652605459057073,"theoretical_boost":1.8647290209790208,"shield_score":4,"shield_primes":"3,7,23,53"},{"gap_size":162,"success_rate":0.07064234016887817,"theoretical_boost":1.2196969696969697,"shield_score":2,"shield_primes":"7,23"},{"gap_size":164,"success_rate":0.1613004063769928,"theoretical_boost":2.0625,"shield_score":3,"shield_primes":"3,5,11"},{"gap_size":166,"success_rate":0.16271865889212828,"theoretical_boost":2.0625,"shield_score":3,"shield_primes":"3,5,11"},{"gap_size":168,"success_rate":0.05343698854337152,"theoretical_boost":1.0833333333333333,"shield_score":1,"shield_primes":"13"},{"gap_size":170,"success_rate":0.13096839273705446,"theoretical_boost":1.715277777777778,"shield_score":3,"shield_primes":"3,13,19"},{"gap_size":172,"success_rate":0.10548950164432076,"theoretical_boost":1.5833333333333335,"shield_score":2,"shield_primes":"3,19"},{"gap_size":174,"success_rate":0.09237113402061856,"theoretical_boost":1.4583333333333335,"shield_score":2,"shield_primes":"5,7"},{"gap_size":176,"success_rate":0.18519628408750374,"theoretical_boost":2.225215517241379,"shield_score":4,"shield_primes":"3,5,7,59"},{"gap_size":178,"success_rate":0.09655172413793103,"theoretical_boost":1.5258620689655171,"shield_score":2,"shield_primes":"3,59"},{"gap_size":180,"success_rate":0.05272433543839036,"theoretical_boost":1.0,"shield_score":0,"shield_primes":""},{"gap_size":182,"success_rate":0.09965896172792725,"theoretical_boost":1.525,"shield_score":2,"shield_primes":"3,61"},{"gap_size":184,"success_rate":0.16666666666666666,"theoretical_boost":1.9592013888888884,"shield_score":4,"shield_primes":"3,5,37,61"},{"gap_size":186,"success_rate":0.09150149334781428,"theoretical_boost":1.501519097222222,"shield_score":4,"shield_primes":"5,11,17,37"},{"gap_size":188,"success_rate":0.1497005988023952,"theoretical_boost":2.0453125,"shield_score":4,"shield_primes":"3,7,11,17"},{"gap_size":190,"success_rate":0.1409308394954328,"theoretical_boost":1.75,"shield_score":2,"shield_primes":"3,7"},{"gap_size":192,"success_rate":0.05873261205564142,"theoretical_boost":1.0,"shield_score":0,"shield_primes":""},{"gap_size":194,"success_rate":0.14506437768240343,"theoretical_boost":2.03125,"shield_score":3,"shield_primes":"3,5,13"},{"gap_size":196,"success_rate":0.1634768740031898,"theoretical_boost":2.03125,"shield_score":3,"shield_primes":"3,5,13"},{"gap_size":198,"success_rate":0.03438530381535563,"theoretical_boost":1.0,"shield_score":0,"shield_primes":""},{"gap_size":200,"success_rate":0.10344827586206896,"theoretical_boost":1.5227272727272727,"shield_score":2,"shield_primes":"3,67"},{"gap_size":202,"success_rate":0.13990267639902676,"theoretical_boost":1.8399621212121213,"shield_score":4,"shield_primes":"3,7,29,67"},{"gap_size":204,"success_rate":0.10932025227750526,"theoretical_boost":1.5481770833333335,"shield_score":4,"shield_primes":"5,7,29,41"},{"gap_size":206,"success_rate":0.17411402157164868,"theoretical_boost":2.009232954545454,"shield_score":4,"shield_primes":"3,5,23,41"},{"gap_size":208,"success_rate":0.11669128508124077,"theoretical_boost":1.8208333333333335,"shield_score":4,"shield_primes":"3,11,19,23"},{"gap_size":210,"success_rate":0.06531678641410843,"theoretical_boost":1.1611111111111112,"shield_score":2,"shield_primes":"11,19"},{"gap_size":212,"success_rate":0.11488250652741515,"theoretical_boost":1.5214285714285714,"shield_score":2,"shield_primes":"3,71"},{"gap_size":214,"success_rate":0.1404494382022472,"theoretical_boost":1.947066326530612,"shield_score":4,"shield_primes":"3,5,43,71"},{"gap_size":216,"success_rate":0.08682170542635659,"theoretical_boost":1.5428240740740742,"shield_score":4,"shield_primes":"5,7,31,43"},{"gap_size":218,"success_rate":0.09666666666666666,"theoretical_boost":1.8334490740740743,"shield_score":4,"shield_primes":"3,7,31,73"},{"gap_size":220,"success_rate":0.1201923076923077,"theoretical_boost":1.750542534722222,"shield_score":4,"shield_primes":"3,13,17,73"},{"gap_size":222,"success_rate":0.06464646464646465,"theoretical_boost":1.1510416666666665,"shield_score":2,"shield_primes":"13,17"},{"gap_size":224,"success_rate":0.128,"theoretical_boost":1.875,"shield_score":2,"shield_primes":"3,5"},{"gap_size":226,"success_rate":0.12745098039215685,"theoretical_boost":1.875,"shield_score":2,"shield_primes":"3,5"},{"gap_size":228,"success_rate":0.05945945945945946,"theoretical_boost":1.0,"shield_score":0,"shield_primes":""},{"gap_size":230,"success_rate":0.11330049261083744,"theoretical_boost":1.9250000000000003,"shield_score":3,"shield_primes":"3,7,11"},{"gap_size":232,"success_rate":0.0948905109489051,"theoretical_boost":1.9250000000000003,"shield_score":3,"shield_primes":"3,7,11"},{"gap_size":234,"success_rate":0.0627062706270627,"theoretical_boost":1.2771739130434785,"shield_score":2,"shield_primes":"5,47"},{"gap_size":236,"success_rate":0.13157894736842105,"theoretical_boost":1.9403219063545152,"shield_score":4,"shield_primes":"3,5,47,79"},{"gap_size":238,"success_rate":0.08955223880597014,"theoretical_boost":1.5192307692307692,"shield_score":2,"shield_primes":"3,79"},{"gap_size":240,"success_rate":0.04205607476635514,"theoretical_boost":1.0,"shield_score":0,"shield_primes":""},{"gap_size":242,"success_rate":0.09210526315789473,"theoretical_boost":1.5,"shield_score":1,"shield_primes":"3"},{"gap_size":244,"success_rate":0.16455696202531644,"theoretical_boost":2.1875,"shield_score":3,"shield_primes":"3,5,7"},{"gap_size":246,"success_rate":0.10416666666666667,"theoretical_boost":1.6676311728395063,"shield_score":4,"shield_primes":"5,7,13,19"},{"gap_size":248,"success_rate":0.0821917808219178,"theoretical_boost":1.7361957994579946,"shield_score":4,"shield_primes":"3,13,19,83"},{"gap_size":250,"success_rate":0.16071428571428573,"theoretical_boost":1.5182926829268293,"shield_score":2,"shield_primes":"3,83"},{"gap_size":252,"success_rate":0.0546875,"theoretical_boost":1.1500000000000001,"shield_score":2,"shield_primes":"11,23"},{"gap_size":254,"success_rate":0.06451612903225806,"theoretical_boost":2.291015625,"shield_score":5,"shield_primes":"3,5,11,17,23"},{"gap_size":256,"success_rate":0.1951219512195122,"theoretical_boost":1.9921875,"shield_score":3,"shield_primes":"3,5,17"},{"gap_size":258,"success_rate":0.042105263157894736,"theoretical_boost":1.199074074074074,"shield_score":2,"shield_primes":"7,37"},{"gap_size":260,"success_rate":0.18604651162790697,"theoretical_boost":1.8628472222222223,"shield_score":4,"shield_primes":"3,7,29,37"},{"gap_size":262,"success_rate":0.10344827586206896,"theoretical_boost":1.5535714285714288,"shield_score":2,"shield_primes":"3,29"},{"gap_size":264,"success_rate":0.1320754716981132,"theoretical_boost":1.2740384615384615,"shield_score":2,"shield_primes":"5,53"},{"gap_size":266,"success_rate":0.28125,"theoretical_boost":1.9327742569930069,"shield_score":4,"shield_primes":"3,5,53,89"},{"gap_size":268,"success_rate":0.13043478260869565,"theoretical_boost":1.5170454545454546,"shield_score":2,"shield_primes":"3,89"},{"gap_size":270,"success_rate":0.023809523809523808,"theoretical_boost":1.0,"shield_score":0,"shield_primes":""},{"gap_size":272,"success_rate":0.26666666666666666,"theoretical_boost":1.8958333333333333,"shield_score":3,"shield_primes":"3,7,13"},{"gap_size":274,"success_rate":0.3125,"theoretical_boost":2.606770833333333,"shield_score":5,"shield_primes":"3,5,7,11,13"},{"gap_size":278,"success_rate":0.1111111111111111,"theoretical_boost":1.5500000000000003,"shield_score":2,"shield_primes":"3,31"},{"gap_size":280,"success_rate":0.3125,"theoretical_boost":1.5500000000000003,"shield_score":2,"shield_primes":"3,31"},{"gap_size":282,"success_rate":0.05555555555555555,"theoretical_boost":1.0,"shield_score":0,"shield_primes":""},{"gap_size":284,"success_rate":0.125,"theoretical_boost":1.9791666666666667,"shield_score":3,"shield_primes":"3,5,19"},{"gap_size":286,"success_rate":0.3333333333333333,"theoretical_boost":2.366753472222222,"shield_score":5,"shield_primes":"3,5,7,19,41"},{"gap_size":288,"success_rate":0.2,"theoretical_boost":1.2705729166666666,"shield_score":3,"shield_primes":"7,17,41"},{"gap_size":290,"success_rate":0.15384615384615385,"theoretical_boost":1.6103515625000002,"shield_score":3,"shield_primes":"3,17,97"},{"gap_size":296,"success_rate":0.3333333333333333,"theoretical_boost":2.098060344827586,"shield_score":4,"shield_primes":"3,5,11,59"},{"gap_size":300,"success_rate":0.16666666666666666,"theoretical_boost":1.3527988215488211,"shield_score":4,"shield_primes":"7,13,23,43"},{"gap_size":302,"success_rate":0.25,"theoretical_boost":1.7916666666666665,"shield_score":3,"shield_primes":"3,7,43"},{"gap_size":304,"success_rate":0.3333333333333333,"theoretical_boost":1.90625,"shield_score":3,"shield_primes":"3,5,61"},{"gap_size":312,"success_rate":0.3333333333333333,"theoretical_boost":1.0,"shield_score":0,"shield_primes":""},{"gap_size":322,"success_rate":0.5,"theoretical_boost":1.6822916666666667,"shield_score":3,"shield_primes":"3,17,19"}]
